diffbot_kg/__init__.py
diffbot_kg/clients/__init__.py
diffbot_kg/clients/base.py
diffbot_kg/clients/enhance.py
diffbot_kg/clients/search.py
diffbot_kg/clients/session.py
diffbot_kg/models/response/__init__.py
diffbot_kg/models/response/base.py
diffbot_kg/models/response/bulkjob_create.py
diffbot_kg/models/response/bulkjob_list.py
diffbot_kg/models/response/bulkjob_results.py
diffbot_kg/models/response/bulkjob_status.py
diffbot_kg/models/response/coverage_report.py
diffbot_kg/models/response/entities.py
diffbot_kg-0.2.4.dist-info/LICENSE
diffbot_kg-0.2.4.dist-info/METADATA
diffbot_kg-0.2.4.dist-info/WHEEL
diffbot_kg-0.2.4.dist-info/RECORD
