Metadata-Version: 2.1
Name: diffbot-kg
Version: 0.2.4
Summary: Python client for the Diffbot Knowledge Graph API.
License: MIT
Author: Brendan C. Smith
Requires-Python: >=3.11,<4.0
Classifier: License :: OSI Approved :: MIT License
Classifier: Programming Language :: Python :: 3
Classifier: Programming Language :: Python :: 3.11
Classifier: Programming Language :: Python :: 3.12
Requires-Dist: aiohttp (>=3.9.3,<4.0.0)
Requires-Dist: aiolimiter (>=1.1.0,<2.0.0)
Requires-Dist: tenacity (>=8.2.3,<9.0.0)
Requires-Dist: yarl (>=1.9.4,<2.0.0)
